flask_rest_api/.__init__.py.swp
flask_rest_api/__init__.py
flask_rest_api/args_parser.py
flask_rest_api/arguments.py
flask_rest_api/blueprint.py
flask_rest_api/compat.py
flask_rest_api/error_handler.py
flask_rest_api/etag.py
flask_rest_api/exceptions.py
flask_rest_api/fields.py
flask_rest_api/pagination.py
flask_rest_api/response.py
flask_rest_api/utils.py
flask_rest_api/spec/__init__.py
flask_rest_api/spec/field_converters.py
flask_rest_api/spec/plugin.py
flask_rest_api/spec/plugins.py
flask_rest_api/spec/templates/redoc.html
flask_rest_api/spec/templates/swagger_ui.html
flask_rest_api-0.17.1.dist-info/AUTHORS.rst
flask_rest_api-0.17.1.dist-info/LICENSE
flask_rest_api-0.17.1.dist-info/METADATA
flask_rest_api-0.17.1.dist-info/WHEEL
flask_rest_api-0.17.1.dist-info/top_level.txt
flask_rest_api-0.17.1.dist-info/RECORD
