Metadata-Version: 1.2
Name: flask-rest-api
Version: 0.17.1
Summary: Build a REST API with Flask
Home-page: https://github.com/Nobatek/flask-rest-api
Author: Jérôme Lafréchoux
Author-email: jlafrechoux@nobatek.com
License: MIT
Keywords: REST,openapi,swagger,flask,marshmallow,apispecwebargs
Platform: UNKNOWN
Classifier: Development Status :: 4 - Beta
Classifier: Intended Audience :: Developers
Classifier: Topic :: Internet :: WWW/HTTP
Classifier: Environment :: Web Environment
Classifier: Framework :: Flask
Classifier: License :: OSI Approved :: MIT License
Classifier: Programming Language :: Python :: 3.5
Classifier: Programming Language :: Python :: 3.6
Classifier: Programming Language :: Python :: 3.7
Requires-Python: >=3.5
